Metadata-Version: 2.1
Name: django-next-view
Version: 2020.7.1
Summary: Django view redirect mixin ?next=url
Home-page: https://github.com/andrewp-as-is/django-next-view.py
License: Unlicense
Keywords: django view redirect
Platform: UNKNOWN
Classifier: Framework :: Django
Classifier: License :: Public Domain
Classifier: Operating System :: OS Independent
Classifier: Programming Language :: Python :: 3
